uzgeo/__init__.py
uzgeo/common.py
uzgeo/uzgeo.py
uzgeo-0.3.0.dist-info/LICENSE
uzgeo-0.3.0.dist-info/METADATA
uzgeo-0.3.0.dist-info/WHEEL
uzgeo-0.3.0.dist-info/entry_points.txt
uzgeo-0.3.0.dist-info/top_level.txt
uzgeo-0.3.0.dist-info/RECORD
